extract_code_jupyter/__init__.py
extract_code_jupyter/cli.py
extract_code_jupyter/extractor.py
tests/__init__.py
tests/test_extractor.py
jupyter_code_extractor-0.1.2.dist-info/LICENSE
jupyter_code_extractor-0.1.2.dist-info/METADATA
jupyter_code_extractor-0.1.2.dist-info/WHEEL
jupyter_code_extractor-0.1.2.dist-info/entry_points.txt
jupyter_code_extractor-0.1.2.dist-info/top_level.txt
jupyter_code_extractor-0.1.2.dist-info/RECORD
