Metadata-Version: 2.1
Name: jupyter-code-extractor
Version: 0.1.2
Summary: CLI tool to extract the code cells of a jupyter notebook into a .txt file.
Home-page: https://github.com/RealWorga/jupyter-code-extractor
Author: Hamed Haghjo
Author-email: hamedhaghjo@hotmail.com
Classifier: Programming Language :: Python :: 3
Classifier: License :: OSI Approved :: MIT License
Classifier: Operating System :: OS Independent
License-File: LICENSE
